cruxy/__init__.py
cruxy/optimizer.py
cruxy/controllers/__init__.py
cruxy/controllers/meta_controller.py
cruxy/controllers/v1_controller.py
cruxy/controllers/v2_controller.py
cruxy/core/__init__.py
cruxy/core/curvature.py
cruxy/core/phase.py
cruxy/core/variance.py
cruxy/utils/__init__.py
cruxy/utils/metrics.py
cruxy/utils/safety.py
cruxy-2.1.0.dist-info/licenses/LICENSE
cruxy-2.1.0.dist-info/METADATA
cruxy-2.1.0.dist-info/WHEEL
cruxy-2.1.0.dist-info/top_level.txt
cruxy-2.1.0.dist-info/RECORD
