Metadata-Version: 2.4
Name: Cruxy
Version: 2.1.0
Summary: Cruxy Stability Engine - Adaptive optimization framework by Axiom Forge Systems
Home-page: https://github.com/christophergardner-star/Crux1
Author: Axiom Forge Systems Ltd
Author-email: Axiom Forge Systems Ltd <dev@axiomforge.ai>
License: Apache-2.0
Classifier: Development Status :: 4 - Beta
Classifier: Intended Audience :: Science/Research
Classifier: License :: OSI Approved :: Apache Software License
Classifier: Programming Language :: Python :: 3
Classifier: Topic :: Scientific/Engineering :: Artificial Intelligence
Requires-Python: >=3.8
License-File: LICENSE
Requires-Dist: torch>=2.0.0
Requires-Dist: numpy>=1.20.0
Provides-Extra: dev
Requires-Dist: pytest>=7.0.0; extra == "dev"
Dynamic: author
Dynamic: home-page
Dynamic: license-file
Dynamic: requires-python
